xy_web_server/ModuleData.py
xy_web_server/WebServerWork.py
xy_web_server/Work.py
xy_web_server/__init__.py
xy_web_server/Backup/Backup.py
xy_web_server/Backup/__init__.py
xy_web_server/Database/Database.py
xy_web_server/Database/__init__.py
xy_web_server/Database/Connector/__init__.py
xy_web_server/Database/Connector/Mysql/Mysql.py
xy_web_server/Database/Connector/Mysql/__init__.py
xy_web_server/Database/Connector/Sqlite/Sqlite.py
xy_web_server/Database/Sql/Sql.py
xy_web_server/Log/Log.py
xy_web_server/Log/__init__.py
xy_web_server/Server/Server.py
xy_web_server/Server/__init__.py
xy_web_server/Server/Django/Django.py
xy_web_server/Server/Django/__init__.py
xy_web_server/Server/Nginx/Nginx.py
xy_web_server/Server/Nginx/__init__.py
xy_web_server/Server/Tornado/Tornado.py
xy_web_server/Server/Tornado/__init__.py
xy_web_server/Server/Uwsgi/Uwsgi.py
xy_web_server/Server/Uwsgi/__init__.py
xy_web_server/Settings/Settings.py
xy_web_server/Settings/__init__.py
xy_web_server/Settings/Section/Django.py
xy_web_server/Settings/Section/Nginx.py
xy_web_server/Settings/Section/Section.py
xy_web_server/Settings/Section/Tornado.py
xy_web_server/Settings/Section/Uwsgi.py
xy_web_server/Settings/Section/__init__.py
xy_web_server/data/template/config/xy_web_server_toml.template
xy_web_server/data/template/runner/runner_py.template
xy_web_server/execute/Main.py
xy_web_server/execute/__init__.py
xy_web_server-1.0.3.dist-info/LICENSE
xy_web_server-1.0.3.dist-info/METADATA
xy_web_server-1.0.3.dist-info/WHEEL
xy_web_server-1.0.3.dist-info/entry_points.txt
xy_web_server-1.0.3.dist-info/top_level.txt
xy_web_server-1.0.3.dist-info/RECORD
